{
    "courses": [
        {
            "id": "khkt-hinh-su",
            "title": "18 Chuyên Đề Khoa Học Kỹ Thuật Hình Sự",
            "desc": "Trường Đại học Cảnh sát Điều tra Hình sự Trung Quốc (Criminal Investigation Police University of China)",
            "tag": "Khoa Học Hình Sự",
            "image": "",
            "price": "3,990,000",
            "benefits": [
                "Hệ thống hóa kiến thức về khoa học kỹ thuật hình sự.",
                "Nắm vững kỹ thuật giám định dấu vết, tài liệu, hình ảnh và pháp y.",
                "Phân tích thực tiễn từ các vụ án thực tế.",
                "Kỹ năng thu thập và giám định vật chứng chuyên nghiệp."
            ],
            "target": "Sinh viên ngành điều tra hình sự, cán bộ pháp y, nhân sự kỹ thuật hình sự và những ai quan tâm đến khoa học hình sự.",
            "syllabus": [
                {
                    "title": "Chuyên đề 1: Lý luận cơ bản về Khoa học Kỹ thuật Hình sự",
                    "children": [
                        "[Video] 1.1 Khái quát về Kỹ thuật Hình sự",
                        "[Video] 1.2 Nguyên lý Locard",
                        "[Video] 1.3 Giám định chủng loại và Giám định đồng nhất"
                    ]
                },
                {
                    "title": "Chuyên đề 2: Giám định dấu tay (Vân tay)",
                    "children": [
                        "[Video] 2.1 Đặc tính của dấu tay",
                        "[Video] 2.2 Cấu trúc và Đặc điểm của đường vân (Vân tuyến)",
                        "[Video] 2.3 Các đặc điểm vết in hoa văn khác",
                        "[Video] 2.4 Kỹ thuật phát hiện dấu tay ẩn bằng phương pháp xông hơi/hóa chất",
                        "[Video] 2.5 Phân tích dấu tay"
                    ]
                },
                {
                    "title": "Chuyên đề 3: Giám định dấu chân",
                    "children": [
                        "[Video] 3.1 Đặc điểm hình dạng dấu chân",
                        "[Video] 3.2 Đặc điểm bộ pháp",
                        "[Video] 3.3 Thu thập dấu chân tại hiện trường"
                    ]
                },
                {
                    "title": "Chuyên đề 4: Giám định dấu vết công cụ gây án",
                    "children": [
                        "[Video] 4.1 Hai loại dấu vết công cụ",
                        "[Video] 4.2 Giám định dấu vết cạy, ép",
                        "[Video] 4.3 Giám định dấu vết cắt, kẹp"
                    ]
                },
                {
                    "title": "Chuyên đề 5: Giám định dấu vết súng đạn",
                    "children": [
                        "[Video] 5.1 Súng và đạn",
                        "[Video] 5.2 Dấu vết trên đầu đạn",
                        "[Video] 5.3 Dấu vết trên vỏ đạn"
                    ]
                },
                {
                    "title": "Chuyên đề 6: Giám định và định danh dấu vết tổng hợp",
                    "children": [
                        "[Video] 6.1 Giám định dấu vết thân thể",
                        "[Video] 6.2 Giám định dấu vết công cụ"
                    ]
                },
                {
                    "title": "Chuyên đề 7: Giám định bút tích (Chữ viết)",
                    "children": [
                        "[Video] 7.1 Giám định tài liệu",
                        "[Video] 7.2 Chữ viết và cơ chế hình thành chữ viết",
                        "[Video] 7.3 Đặc điểm chung của chữ viết",
                        "[Video] 7.4 Đặc điểm bố cục trình bày",
                        "[Video] 7.5 Đặc điểm về cách viết",
                        "[Video] 7.6 Đặc điểm về lỗi chính tả và sai sót văn bản",
                        "[Video] 7.7 Đặc điểm về tỷ lệ kết cấu và vận động bút",
                        "[Video] 7.8 Đặc điểm về thứ tự các nét"
                    ]
                },
                {
                    "title": "Chuyên đề 8: Giám định tài liệu in",
                    "children": [
                        "[Video] 8.1 Tổng quan về giám định tài liệu in",
                        "[Video] 8.2 Nguyên lý máy photocopy tĩnh điện"
                    ]
                },
                {
                    "title": "Chuyên đề 9: Cơ sở giám định tư liệu âm thanh, hình ảnh",
                    "children": [
                        "[Video] 9.1 Khái quát về giám định tư liệu âm thanh, hình ảnh",
                        "[Video] 9.2 Các yếu tố ảnh hưởng đến độ phơi sáng",
                        "[Video] 9.3 Cách kiểm soát độ sâu trường ảnh",
                        "[Video] 9.4 Sức hấp dẫn của ánh sáng"
                    ]
                },
                {
                    "title": "Chuyên đề 10: Nhiếp ảnh hiện trường",
                    "children": [
                        "[Video] 10.1 Khái quát về nhiếp ảnh hiện trường",
                        "[Video] 10.2 Cách chụp ảnh hiện trường vụ án",
                        "[Video] 10.3 Nhiếp ảnh chi tiết hiện trường"
                    ]
                },
                {
                    "title": "Chuyên đề 11: Nhiếp ảnh vật chứng",
                    "children": [
                        "[Video] 11.1 Khái quát về nhiếp ảnh giám định vật chứng",
                        "[Video] 11.2 Nhiếp ảnh phân sắc",
                        "[Video] 11.3 Nhiếp ảnh ánh sáng phân cực",
                        "[Video] 11.4 Nhiếp ảnh tăng cường độ tương phản",
                        "[Video] 11.5 Kỹ thuật nhiếp ảnh hồng ngoại",
                        "[Video] 11.6 Kỹ thuật nhiếp ảnh tử ngoại"
                    ]
                },
                {
                    "title": "Chuyên đề 12: Phân tích vật chứng vi lượng",
                    "children": [
                        "[Video] 12.1 Tổng quan về phân tích vật chứng vi lượng",
                        "[Video] 12.2 Tìm kiếm và thu thập vật chứng vi lượng tại hiện trường",
                        "[Video] 12.3 Nội dung và phương pháp giám định vật chứng vi lượng",
                        "[Video] 12.4 Thu mẫu và giám định vật chứng vi lượng trong vụ án hỏa hoạn",
                        "[Video] 12.5 Thu mẫu và giám định vật chứng vi lượng trong vụ án súng đạn",
                        "[Video] 12.6 Thu mẫu và giám định vật chứng vi lượng trong vụ án nổ",
                        "[Video] 12.7 Thu mẫu và giám định vật chứng vi lượng trong tai nạn giao thông"
                    ]
                },
                {
                    "title": "Chuyên đề 13: Phân tích chất độc",
                    "children": [
                        "[Video] 13.1 Tổng quan về phân tích chất độc",
                        "[Video] 13.2 Phân loại chất độc",
                        "[Video] 13.3 Ngộ độc chất độc",
                        "[Video] 13.4 Triệu chứng ngộ độc chất độc",
                        "[Video] 13.5 Quá trình của chất độc trong cơ thể",
                        "[Video] 13.6 Phát hiện, thu thập và bảo quản vật chứng chất độc",
                        "[Video] 13.7 Nội dung cơ bản của giám định chất độc",
                        "[Video] 13.8 Quy trình cơ bản của giám định chất độc"
                    ]
                },
                {
                    "title": "Chuyên đề 14: Phân tích ma túy",
                    "children": [
                        "[Video] 14.1 Tổng quan về phân tích ma túy",
                        "[Video] 14.2 Quy định về lấy mẫu và bảo quản ma túy",
                        "[Video] 14.3 Kiểm tra nhanh ma túy tại hiện trường",
                        "[Video] 14.4 Yêu cầu lấy mẫu đối với người lạm dụng ma túy",
                        "[Video] 14.5 Kiểm nghiệm ma túy và các chất chuyển hóa của chúng trong phòng thí nghiệm"
                    ]
                },
                {
                    "title": "Chuyên đề 15: Khái quát về Pháp y học",
                    "children": [
                        "[Video] 15.1 Đại cương Pháp y học"
                    ]
                },
                {
                    "title": "Chuyên đề 16: Các hiện tượng tử thi",
                    "children": [
                        "[Video] 16.1 Hiện tượng tử thi — Những thay đổi sau khi chết"
                    ]
                },
                {
                    "title": "Chuyên đề 17: Các dạng thương tích",
                    "children": [
                        "[Video] 17.1 Vết đâm — Tổn thương chí mạng do vật sắc nhọn",
                        "[Video] 17.2 Rơi từ trên cao dẫn đến tử vong",
                        "[Video] 17.3 Giám định pháp y đối với thi thể dưới nước",
                        "[Video] 17.4 Giám định pháp y đối với thi thể trong đám cháy",
                        "[Video] 17.5 Giám định pháp y tổn thương do điện giật"
                    ]
                },
                {
                    "title": "Chuyên đề 18: Giám định pháp y",
                    "children": [
                        "[Video] 18.1 Đột tử — Cái chết bất ngờ ngoài ý muốn",
                        "[Video] 18.2 Suy đoán thời gian tử vong",
                        "[Video] 18.3 Suy đoán vật gây thương tích"
                    ]
                }
            ]
        }
    ],
    "faq": [
        {
            "q": "Hình thức nhận bài giảng như thế nào?",
            "a": "Admin sẽ mời email của bạn vào Google Drive chứa đầy đủ video và tài liệu."
        },
        {
            "q": "Bài giảng có vietsub không?",
            "a": "Tất cả bài giảng từ nguồn nước ngoài đều được biên dịch và lồng ghép vietsub chuẩn chỉnh."
        },
        {
            "q": "Có hỗ trợ chuyên môn sau khi học không?",
            "a": "Bạn có thể nhắn tin cho chúng tôi bất cứ lúc nào để trao đổi về các vấn đề chuyên môn."
        }
    ]
}
